push7/__init__.py
push7/client.py
push7/exceptions.py
push7/push.py
push7-0.0.6.dist-info/DESCRIPTION.rst
push7-0.0.6.dist-info/METADATA
push7-0.0.6.dist-info/RECORD
push7-0.0.6.dist-info/WHEEL
push7-0.0.6.dist-info/metadata.json
push7-0.0.6.dist-info/top_level.txt
