Metadata-Version: 2.0
Name: push7
Version: 0.0.6
Summary: Python API Client for Push7
Home-page: https://github.com/a-r-g-v/push7-python
Author: a_r_g_v
Author-email: info@arg.vc
License: MIT
Keywords: push7
Platform: UNKNOWN
Requires-Dist: enum34
Requires-Dist: requests
Requires-Dist: simplejson
Requires-Dist: six
Requires-Dist: typing
